sprouter/__init__.py
sprouter/cli.py
sprouter/core.py
sprouter-0.1.4.dist-info/licenses/LICENSE.md
sprouter-0.1.4.dist-info/METADATA
sprouter-0.1.4.dist-info/WHEEL
sprouter-0.1.4.dist-info/entry_points.txt
sprouter-0.1.4.dist-info/top_level.txt
sprouter-0.1.4.dist-info/RECORD
