Metadata-Version: 2.4
Name: sprouter
Version: 0.1.4
Summary: Simple Python project bootstrapper with virtualenv and pip automation.
Author-email: "</gadget_saavy>" <c.hirschauer@gmail.com>
License-File: LICENSE.md
Dynamic: license-file
